django_fallback_storage-1.1.1.dist-info/DESCRIPTION.rst
django_fallback_storage-1.1.1.dist-info/METADATA
django_fallback_storage-1.1.1.dist-info/RECORD
django_fallback_storage-1.1.1.dist-info/WHEEL
django_fallback_storage-1.1.1.dist-info/metadata.json
django_fallback_storage-1.1.1.dist-info/top_level.txt
fallback_storage/__init__.py
fallback_storage/config.py
fallback_storage/models.py
fallback_storage/storage.py
