Metadata-Version: 2.0
Name: django-fallback-storage
Version: 1.1.1
Summary: Multiple Storage Engines
Home-page: https://github.com/pipermerriam/django-fallback-storage
Author: Piper Merriam
Author-email: pipermerriam@gmail.com
License: MIT
Keywords: django-fallback-storage
Platform: UNKNOWN
Classifier: Development Status :: 2 - Pre-Alpha
Classifier: Framework :: Django
Classifier: Intended Audience :: Developers
Classifier: License :: OSI Approved :: BSD License
Classifier: Natural Language :: English
Classifier: Programming Language :: Python :: 2
Classifier: Programming Language :: Python :: 2.6
Classifier: Programming Language :: Python :: 2.7
Classifier: Programming Language :: Python :: 3
Classifier: Programming Language :: Python :: 3.3
Requires-Dist: Django (<1.12,>=1.6)
